tringa/__init__.py
tringa/db.py
tringa/exceptions.py
tringa/fetch.py
tringa/gh.py
tringa/models.py
tringa/msg.py
tringa/queries.py
tringa/repl.py
tringa/scoped_db.py
tringa/utils.py
tringa/annotations/__init__.py
tringa/annotations/flaky.py
tringa/cli/__init__.py
tringa/cli/cli.py
tringa/cli/output.py
tringa/cli/internals/__init__.py
tringa/cli/internals/cli.py
tringa/cli/pr/__init__.py
tringa/cli/pr/cli.py
tringa/cli/repo/__init__.py
tringa/cli/repo/cli.py
tringa/cli/repo/show.py
tringa/cli/reports/__init__.py
tringa/cli/reports/failed_tests.py
tringa/cli/reports/flaky_tests.py
tringa/cli/reports/slow_tests.py
tringa/cli/reports/status_checks.py
tringa/cli/run/__init__.py
tringa/cli/run/cli.py
tringa/cli/run/show.py
tringa/tui/tringa.tcss
tringa/tui/tui.py
tringa-0.2.0.dist-info/METADATA
tringa-0.2.0.dist-info/WHEEL
tringa-0.2.0.dist-info/entry_points.txt
tringa-0.2.0.dist-info/RECORD
