Metadata-Version: 2.3
Name: tringa
Version: 0.2.0
Summary: A tool for querying test output across multiple CI builds on GitHub
Requires-Python: >=3.12
Requires-Dist: duckdb>=1.0.0
Requires-Dist: humanize>=4.10.0
Requires-Dist: ipython>=8.26.0
Requires-Dist: junitparser>=3.1.2
Requires-Dist: pandas>=2.2.2
Requires-Dist: pytest>=8.3.2
Requires-Dist: rich>=13.8.0
Requires-Dist: textual-dev>=1.6.1
Requires-Dist: textual-serve>=1.1.1
Requires-Dist: textual>=0.79.1
Requires-Dist: typer>=0.12.5
Requires-Dist: xdg-base-dirs>=6.0.1
